{
  "player": "Trey McBride",
  "gsis_id": "00-0037744",
  "position": "TE",
  "team": "ARI",
  "display_name": "T.McBride",
  "game": {
    "game_id": "597e7fb5542c56bda7f1a73402cd47e0",
    "home_team": "Arizona Cardinals",
    "away_team": "Chicago Bears",
    "commence_time": "2024-11-03T21:05:00Z"
  },
  "props": {
    "Receiving Yards": {
      "line": 51.5,
      "over_price": -137,
      "under_price": -137
    }
  },
  "metadata": {
    "timestamp": "2025-11-03T12:28:57.178023",
    "season": 2024,
    "week": 8,
    "day": "tuesday",
    "bookmaker": "prizepicks",
    "last_update": "2024-10-29T12:56:14Z"
  }
}